rope_omni.py
ropevim.py
ropevim-0.8.0.dist-info/COPYING
ropevim-0.8.0.dist-info/METADATA
ropevim-0.8.0.dist-info/WHEEL
ropevim-0.8.0.dist-info/top_level.txt
ropevim-0.8.0.dist-info/RECORD
