Metadata-Version: 2.1
Name: ropevim
Version: 0.8.0
Summary: A vim plugin for using rope python refactoring library
Home-page: http://rope.sf.net/ropevim.html
Author: Ali Gholami Rudi
Author-email: aligrudi@users.sourceforge.net
Maintainer: Matej Cepl
Maintainer-email: mcepl@cepl.eu
License: GNU GPL
Platform: UNKNOWN
Classifier: Development Status :: 6 - Mature
Classifier: Programming Language :: Python :: 3.5
Classifier: Programming Language :: Python :: 3.6
Classifier: Programming Language :: Python :: 3.7
Classifier: Operating System :: OS Independent
Classifier: Environment :: X11 Applications
Classifier: Environment :: Win32 (MS Windows)
Classifier: Environment :: MacOS X
Classifier: Intended Audience :: Developers
Classifier: License :: OSI Approved :: GNU General Public License (GPL)
Classifier: Natural Language :: English
Classifier: Topic :: Software Development
Requires: ropemode
Requires-Dist: rope (>=0.9.3)
Requires-Dist: ropemode
